{
  "$schema": "http://json-schema.org/draft-07/schema#",
  "additionalProperties": false,
  "definitions": {
    "color": {
      "anyOf": [
        {
          "maximum": 255,
          "minimum": 0,
          "type": "integer"
        },
        {
          "type": "null"
        },
        {
          "enum": [
            "Bright Amber",
            "Cornflower Blue",
            "Cyan / Aqua",
            "Dark Blue",
            "Dark Gold",
            "Dark Goldenrod",
            "Deep Blue",
            "Dodger Blue",
            "Electric Blue",
            "Light Blue",
            "Midnight Blue",
            "Navy Blue",
            "Orange-Brown",
            "Pale Ice Blue",
            "Powder Blue",
            "Rose Pink",
            "Royal Blue",
            "Sky Blue",
            "Steel Blue",
            "amb",
            "amber",
            "azr",
            "azure",
            "bab",
            "bbk",
            "bbl",
            "bcy",
            "bgn",
            "bgry",
            "black",
            "blk",
            "blu",
            "blue",
            "bmg",
            "brd",
            "brightblack",
            "brightblue",
            "brightcyan",
            "brightgray",
            "brightgreen",
            "brightmagenta",
            "brightred",
            "brightyellow",
            "brn",
            "brown",
            "byl",
            "cbl",
            "coral",
            "crimson",
            "crm",
            "cyan",
            "cyn",
            "dark",
            "darkgray",
            "darkgreen",
            "darkmaroon",
            "darknavy",
            "darkolive",
            "darkorange",
            "darkred",
            "darkteal",
            "darkviolet",
            "dbl",
            "dgd",
            "dgn",
            "dgo",
            "dgy",
            "dimgray",
            "dmg",
            "dmr",
            "dnv",
            "dol",
            "dor",
            "dpb",
            "drd",
            "drk",
            "dtl",
            "dvi",
            "ebl",
            "forest",
            "fst",
            "gld",
            "gold",
            "gold2",
            "gray",
            "gray0",
            "gray1",
            "gray10",
            "gray11",
            "gray12",
            "gray13",
            "gray14",
            "gray15",
            "gray16",
            "gray17",
            "gray18",
            "gray19",
            "gray2",
            "gray20",
            "gray21",
            "gray22",
            "gray23",
            "gray3",
            "gray4",
            "gray5",
            "gray6",
            "gray7",
            "gray8",
            "gray9",
            "green",
            "grn",
            "gry",
            "hotpink",
            "hpk",
            "ind",
            "indigo",
            "khaki",
            "khk",
            "lbl",
            "lgy",
            "lightblue",
            "lightgray",
            "lim",
            "lime",
            "mag",
            "magenta",
            "mar",
            "maroon",
            "mgy",
            "midgray",
            "midnight",
            "mint",
            "mnb",
            "mnt",
            "navy",
            "nbl",
            "nvy",
            "obr",
            "oli",
            "olive",
            "orange",
            "org",
            "paleblue",
            "palegreen",
            "paleturquoise",
            "pbl",
            "pgn",
            "pib",
            "pink",
            "plm",
            "plum",
            "pnk",
            "ptq",
            "pur",
            "purple",
            "pwb",
            "rbl",
            "red",
            "rgb000",
            "rgb001",
            "rgb002",
            "rgb003",
            "rgb004",
            "rgb005",
            "rgb010",
            "rgb011",
            "rgb012",
            "rgb013",
            "rgb014",
            "rgb015",
            "rgb020",
            "rgb021",
            "rgb022",
            "rgb023",
            "rgb024",
            "rgb025",
            "rgb030",
            "rgb031",
            "rgb032",
            "rgb033",
            "rgb034",
            "rgb035",
            "rgb040",
            "rgb041",
            "rgb042",
            "rgb043",
            "rgb044",
            "rgb045",
            "rgb050",
            "rgb051",
            "rgb052",
            "rgb053",
            "rgb054",
            "rgb055",
            "rgb100",
            "rgb101",
            "rgb102",
            "rgb103",
            "rgb104",
            "rgb105",
            "rgb110",
            "rgb111",
            "rgb112",
            "rgb113",
            "rgb114",
            "rgb115",
            "rgb120",
            "rgb121",
            "rgb122",
            "rgb123",
            "rgb124",
            "rgb125",
            "rgb130",
            "rgb131",
            "rgb132",
            "rgb133",
            "rgb134",
            "rgb135",
            "rgb140",
            "rgb141",
            "rgb142",
            "rgb143",
            "rgb144",
            "rgb145",
            "rgb150",
            "rgb151",
            "rgb152",
            "rgb153",
            "rgb154",
            "rgb155",
            "rgb200",
            "rgb201",
            "rgb202",
            "rgb203",
            "rgb204",
            "rgb205",
            "rgb210",
            "rgb211",
            "rgb212",
            "rgb213",
            "rgb214",
            "rgb215",
            "rgb220",
            "rgb221",
            "rgb222",
            "rgb223",
            "rgb224",
            "rgb225",
            "rgb230",
            "rgb231",
            "rgb232",
            "rgb233",
            "rgb234",
            "rgb235",
            "rgb240",
            "rgb241",
            "rgb242",
            "rgb243",
            "rgb244",
            "rgb245",
            "rgb250",
            "rgb251",
            "rgb252",
            "rgb253",
            "rgb254",
            "rgb255",
            "rgb300",
            "rgb301",
            "rgb302",
            "rgb303",
            "rgb304",
            "rgb305",
            "rgb310",
            "rgb311",
            "rgb312",
            "rgb313",
            "rgb314",
            "rgb315",
            "rgb320",
            "rgb321",
            "rgb322",
            "rgb323",
            "rgb324",
            "rgb325",
            "rgb330",
            "rgb331",
            "rgb332",
            "rgb333",
            "rgb334",
            "rgb335",
            "rgb340",
            "rgb341",
            "rgb342",
            "rgb343",
            "rgb344",
            "rgb345",
            "rgb350",
            "rgb351",
            "rgb352",
            "rgb353",
            "rgb354",
            "rgb355",
            "rgb400",
            "rgb401",
            "rgb402",
            "rgb403",
            "rgb404",
            "rgb405",
            "rgb410",
            "rgb411",
            "rgb412",
            "rgb413",
            "rgb414",
            "rgb415",
            "rgb420",
            "rgb421",
            "rgb422",
            "rgb423",
            "rgb424",
            "rgb425",
            "rgb430",
            "rgb431",
            "rgb432",
            "rgb433",
            "rgb434",
            "rgb435",
            "rgb440",
            "rgb441",
            "rgb442",
            "rgb443",
            "rgb444",
            "rgb445",
            "rgb450",
            "rgb451",
            "rgb452",
            "rgb453",
            "rgb454",
            "rgb455",
            "rgb500",
            "rgb501",
            "rgb502",
            "rgb503",
            "rgb504",
            "rgb505",
            "rgb510",
            "rgb511",
            "rgb512",
            "rgb513",
            "rgb514",
            "rgb515",
            "rgb520",
            "rgb521",
            "rgb522",
            "rgb523",
            "rgb524",
            "rgb525",
            "rgb530",
            "rgb531",
            "rgb532",
            "rgb533",
            "rgb534",
            "rgb535",
            "rgb540",
            "rgb541",
            "rgb542",
            "rgb543",
            "rgb544",
            "rgb545",
            "rgb550",
            "rgb551",
            "rgb552",
            "rgb553",
            "rgb554",
            "rgb555",
            "ros",
            "rose",
            "rosepink",
            "rpk",
            "sea",
            "seagreen",
            "sie",
            "sienna",
            "sil",
            "silver",
            "sky",
            "skyblue",
            "slate",
            "slt",
            "steelblue",
            "stl",
            "tan",
            "tea",
            "teal",
            "vio",
            "violet",
            "wheat",
            "white",
            "wht",
            "wht2",
            "yellow",
            "ylw"
          ],
          "type": "string"
        },
        {
          "pattern": "^#([0-9a-fA-F]{3}|[0-9a-fA-F]{6})$",
          "type": "string"
        }
      ]
    },
    "palette": {
      "additionalProperties": false,
      "properties": {
        "border_bg": {
          "$ref": "#/definitions/color"
        },
        "border_shade_fg": {
          "$ref": "#/definitions/color"
        },
        "app_bg": {
          "$ref": "#/definitions/color"
        },
        "app_topline_bg": {
          "$ref": "#/definitions/color"
        },
        "emoji_pane_bg": {
          "$ref": "#/definitions/color"
        },
        "scrollbar_rail_bg": {
          "$ref": "#/definitions/color"
        },
        "view_bg": {
          "$ref": "#/definitions/color"
        },
        "grid_bg": {
          "$ref": "#/definitions/color"
        },
        "grid_fg": {
          "$ref": "#/definitions/color"
        },
        "info_bg": {
          "$ref": "#/definitions/color"
        },
        "info_fg": {
          "$ref": "#/definitions/color"
        },
        "search_bg": {
          "$ref": "#/definitions/color"
        },
        "search_fg": {
          "$ref": "#/definitions/color"
        },
        "search_shade_fg": {
          "$ref": "#/definitions/color"
        },
        "search_left_cap_fg": {
          "$ref": "#/definitions/color"
        },
        "search_right_cap_fg": {
          "$ref": "#/definitions/color"
        },
        "search_sep_fg": {
          "$ref": "#/definitions/color"
        },
        "hline_fg": {
          "$ref": "#/definitions/color"
        },
        "selection_bg": {
          "$ref": "#/definitions/color"
        },
        "selection_fg": {
          "$ref": "#/definitions/color"
        },
        "status_bg": {
          "$ref": "#/definitions/color"
        },
        "status_fg": {
          "$ref": "#/definitions/color"
        },
        "status_shade_fg": {
          "$ref": "#/definitions/color"
        },
        "success_fg": {
          "$ref": "#/definitions/color"
        },
        "terminal_bg": {
          "type": "string"
        },
        "terminal_bg2": {
          "type": "string"
        },
        "terminal_border": {
          "type": "string"
        },
        "terminal_fg": {
          "type": "string"
        },
        "warning_fg": {
          "$ref": "#/definitions/color"
        }
      },
      "type": "object"
    }
  },
  "properties": {
    "description": {
      "type": "string"
    },
    "icons": {
      "additionalProperties": false,
      "properties": {
        "dark": {
          "type": "string"
        },
        "light": {
          "type": "string"
        },
        "system": {
          "type": "string"
        }
      },
      "required": [
        "dark",
        "light",
        "system"
      ],
      "type": "object"
    },
    "notes": {
      "type": "object"
    },
    "themes": {
      "additionalProperties": false,
      "properties": {
        "dark": {
          "$ref": "#/definitions/palette"
        },
        "light": {
          "$ref": "#/definitions/palette"
        }
      },
      "required": [
        "dark",
        "light"
      ],
      "type": "object"
    }
  },
  "required": [
    "icons",
    "themes"
  ],
  "type": "object"
}